leaguelosestreakmeter/__init__.py
leaguelosestreakmeter-0.0.2.dist-info/LICENSE
leaguelosestreakmeter-0.0.2.dist-info/METADATA
leaguelosestreakmeter-0.0.2.dist-info/WHEEL
leaguelosestreakmeter-0.0.2.dist-info/top_level.txt
leaguelosestreakmeter-0.0.2.dist-info/RECORD
