Metadata-Version: 2.1
Name: leaguelosestreakmeter
Version: 0.0.2
Summary: Lose streak meter for League of legends
Home-page: http://github.com/fhodun/leaguelosestreakmeter
Author: Filip Hodun
Author-email: filiphodun@gmail.com
License: GPL-3.0
Project-URL: Bug Tracker, https://github.com/pypa/sampleproject/issues
Platform: UNKNOWN
Classifier: Development Status :: 2 - Pre-Alpha
Classifier: Programming Language :: Python :: 3
Classifier: License :: OSI Approved :: GNU General Public License v3 (GPLv3)
Classifier: Operating System :: OS Independent
Requires: r
Requires: i
Requires: o
Requires: t
Requires: w
Requires: a
Requires: t
Requires: c
Requires: h
Requires: e
Requires: r
Requires-Python: >=3.9
Requires-Dist: riotwatcher
